resseg/__init__.py
resseg/features.py
resseg/inference.py
resseg/model.py
resseg/parcellation.py
resseg/resseg.py
resseg/utils.py
resseg/cli/__init__.py
resseg/cli/resseg.py
resseg/cli/resseg_download.py
resseg/cli/resseg_feature_maps.py
resseg/cli/resseg_mni.py
resseg/cli/resseg_patches.py
resseg-0.3.7.dist-info/LICENSE
resseg-0.3.7.dist-info/METADATA
resseg-0.3.7.dist-info/WHEEL
resseg-0.3.7.dist-info/entry_points.txt
resseg-0.3.7.dist-info/top_level.txt
resseg-0.3.7.dist-info/RECORD
