Metadata-Version: 2.1
Name: resseg
Version: 0.3.7
Summary: Automatic segmentation of epilepsy neurosurgery resection cavity.
Home-page: https://github.com/fepegar/resseg
Author: Fernando Perez-Garcia
Author-email: fernando.perezgarcia.17@ucl.ac.uk
License: MIT license
Keywords: resseg
Platform: UNKNOWN
Classifier: Development Status :: 2 - Pre-Alpha
Classifier: Intended Audience :: Developers
Classifier: License :: OSI Approved :: MIT License
Classifier: Natural Language :: English
Classifier: Programming Language :: Python :: 3
Requires-Python: >2.7, !=3.0.*, !=3.1.*, !=3.2.*, !=3.3.*, !=3.4.*
License-File: LICENSE
Requires-Dist: matplotlib
Requires-Dist: pandas
Requires-Dist: torchio
Requires-Dist: unet (==0.7.7)
